meditation_script_generator/__init__.py
meditation_script_generator/meditation_generator.py
meditation_script_generator/meditation_gui.py
meditation_script_generator-1.0.0.dist-info/LICENSE
meditation_script_generator-1.0.0.dist-info/METADATA
meditation_script_generator-1.0.0.dist-info/WHEEL
meditation_script_generator-1.0.0.dist-info/entry_points.txt
meditation_script_generator-1.0.0.dist-info/top_level.txt
meditation_script_generator-1.0.0.dist-info/RECORD
