Metadata-Version: 2.2
Name: meditation-script-generator
Version: 1.0.0
Summary: A meditation script generator with GUI and timer functionality
Home-page: https://github.com/yourusername/meditation-script-generator
Author: Your Name
Author-email: Your Name <your.email@example.com>
License: MIT License
Project-URL: Homepage, https://github.com/yourusername/meditation-script-generator
Project-URL: Repository, https://github.com/yourusername/meditation-script-generator.git
Keywords: meditation,mindfulness,wellness,timer
Classifier: Development Status :: 5 - Production/Stable
Classifier: Intended Audience :: End Users/Desktop
Classifier: License :: OSI Approved :: MIT License
Classifier: Programming Language :: Python :: 3
Classifier: Programming Language :: Python :: 3.7
Classifier: Programming Language :: Python :: 3.8
Classifier: Programming Language :: Python :: 3.9
Classifier: Programming Language :: Python :: 3.10
Classifier: Topic :: Desktop Environment
Classifier: Topic :: Office/Business
Classifier: Topic :: Software Development :: Libraries :: Python Modules
Requires-Python: >=3.7
License-File: LICENSE
Dynamic: author
Dynamic: home-page
Dynamic: requires-python
